<renderuses>
  <renderuse id="_3474" render="0"/><!-- g_signal_newv -->
  <renderuse id="_3475" render="0"/><!-- g_signal_new_valist -->
  <renderuse id="_3476" render="0"/><!-- g_signal_new -->
  <renderuse id="_3477" render="0"/><!-- g_signal_new_class_handler -->
  <renderuse id="_3478" render="0"/><!-- g_signal_set_va_marshaller -->
  <renderuse id="_3479" render="0"/><!-- g_signal_emitv -->
  <renderuse id="_3480" render="0"/><!-- g_signal_emit_valist -->
  <renderuse id="_3481" render="0"/><!-- g_signal_emit -->
  <renderuse id="_3482" render="0"/><!-- g_signal_emit_by_name -->
  <renderuse id="_3483" render="0"/><!-- g_signal_lookup -->
  <renderuse id="_3484" render="0"/><!-- g_signal_name -->
  <renderuse id="_3485" render="0"/><!-- g_signal_query -->
  <renderuse id="_3486" render="0"/><!-- g_signal_list_ids -->
  <renderuse id="_3487" render="0"/><!-- g_signal_is_valid_name -->
  <renderuse id="_3488" render="0"/><!-- g_signal_parse_name -->
  <renderuse id="_3489" render="0"/><!-- g_signal_get_invocation_hint -->
  <renderuse id="_3490" render="0"/><!-- g_signal_stop_emission -->
  <renderuse id="_3491" render="0"/><!-- g_signal_stop_emission_by_name -->
  <renderuse id="_3492" render="0"/><!-- g_signal_add_emission_hook -->
  <renderuse id="_3493" render="0"/><!-- g_signal_remove_emission_hook -->
  <renderuse id="_3494" render="0"/><!-- g_signal_has_handler_pending -->
  <renderuse id="_3495" render="0"/><!-- g_signal_connect_closure_by_id -->
  <renderuse id="_3496" render="0"/><!-- g_signal_connect_closure -->
  <renderuse id="_3497" render="0"/><!-- g_signal_connect_data -->
  <renderuse id="_3498" render="0"/><!-- g_signal_handler_block -->
  <renderuse id="_3499" render="0"/><!-- g_signal_handler_unblock -->
  <renderuse id="_3500" render="0"/><!-- g_signal_handler_disconnect -->
  <renderuse id="_3501" render="0"/><!-- g_signal_handler_is_connected -->
  <renderuse id="_3502" render="0"/><!-- g_signal_handler_find -->
  <renderuse id="_3503" render="0"/><!-- g_signal_handlers_block_matched -->
  <renderuse id="_3504" render="0"/><!-- g_signal_handlers_unblock_matched -->
  <renderuse id="_3505" render="0"/><!-- g_signal_handlers_disconnect_matched -->
  <renderuse id="_3506" render="0"/><!-- g_clear_signal_handler -->
  <renderuse id="_3507" render="0"/><!-- g_signal_override_class_closure -->
  <renderuse id="_3508" render="0"/><!-- g_signal_override_class_handler -->
  <renderuse id="_3509" render="0"/><!-- g_signal_chain_from_overridden -->
  <renderuse id="_3510" render="0"/><!-- g_signal_chain_from_overridden_handler -->
  <renderuse id="_3511" render="0"/><!-- g_signal_accumulator_true_handled -->
  <renderuse id="_3512" render="0"/><!-- g_signal_accumulator_first_wins -->
  <renderuse id="_3513" render="0"/><!-- g_signal_handlers_destroy -->
  <renderuse id="_3514" render="0"/><!-- _g_signals_destroy -->
</renderuses>
